tests/__init__.py
tests/test_winiobinary.py
winiobinary/__init__.py
winiobinary/data/2.0/WINIO.VXD
winiobinary/data/2.0/WinIo.dll
winiobinary/data/2.0/WinIo.sys
winiobinary/data/3.0/DumpPhys.exe
winiobinary/data/3.0/DumpPort.exe
winiobinary/data/3.0/WinIo32.dll
winiobinary/data/3.0/WinIo32.sys
winiobinary/data/3.0/WinIo64.dll
winiobinary/data/3.0/WinIo64.sys
winiobinary-0.0.4.dist-info/DESCRIPTION.rst
winiobinary-0.0.4.dist-info/METADATA
winiobinary-0.0.4.dist-info/RECORD
winiobinary-0.0.4.dist-info/WHEEL
winiobinary-0.0.4.dist-info/metadata.json
winiobinary-0.0.4.dist-info/top_level.txt
